pandavs/__init__.py
pandavs-0.0.1.dist-info/LICENCE.txt
pandavs-0.0.1.dist-info/METADATA
pandavs-0.0.1.dist-info/WHEEL
pandavs-0.0.1.dist-info/top_level.txt
pandavs-0.0.1.dist-info/RECORD
